common/__init__.py
common/arg.py
common/config.py
common/consts.py
common/handle.py
common/log.py
common/task.py
common/utils.py
watchmen/__init__.py
watchmen/main.py
watchmen/args/__init__.py
watchmen/args/generate.py
watchmen/commands/__init__.py
watchmen/commands/add.py
watchmen/commands/base.py
watchmen/commands/list.py
watchmen/commands/pause.py
watchmen/commands/reload.py
watchmen/commands/remove.py
watchmen/commands/restart.py
watchmen/commands/resume.py
watchmen/commands/run.py
watchmen/commands/start.py
watchmen/commands/stop.py
watchmen/engine/__init__.py
watchmen/engine/sock.py
watchmen/utils/__init__.py
watchmen/utils/file.py
watchmen/utils/print_result.py
watchmen/utils/serialize.py
watchmen/utils/types.py
watchmend/__init__.py
watchmend/command.py
watchmend/lib.py
watchmend/main.py
watchmend/monitor.py
watchmend/engine/__init__.py
watchmend/engine/engine.py
watchmend/engine/sock.py
watchmenpy-0.0.1.dist-info/LICENSE
watchmenpy-0.0.1.dist-info/METADATA
watchmenpy-0.0.1.dist-info/WHEEL
watchmenpy-0.0.1.dist-info/entry_points.txt
watchmenpy-0.0.1.dist-info/top_level.txt
watchmenpy-0.0.1.dist-info/RECORD
