Metadata-Version: 2.1
Name: watchmenpy
Version: 0.0.1
Summary: Watchmen is a daemon process manager that for you manage and keep your application online 24/7
Author: ahriknow
Author-email: ahriknow@ahriknow.com
License: MIT
Classifier: Development Status :: 5 - Production/Stable
Classifier: License :: OSI Approved :: MIT License
Classifier: Programming Language :: Python :: 3
Classifier: Programming Language :: Python :: 3.5
Classifier: Programming Language :: Python :: 3.6
Classifier: Programming Language :: Python :: 3.7
Classifier: Programming Language :: Python :: 3.8
Classifier: Programming Language :: Python :: 3.9
Classifier: Programming Language :: Python :: 3.10
Classifier: Programming Language :: Python :: 3.11
Classifier: Programming Language :: Python :: 3.12
Requires-Python: >=3.5
License-File: LICENSE
Requires-Dist: toml ~=0.10.0
Requires-Dist: pydantic ~=2.1.0
Provides-Extra: redis
Requires-Dist: redis <5.0,>=4.5.0 ; extra == 'redis'
